catchm/__init__.py
catchm/embeddings.py
catchm/inductive.py
catchm/model.py
catchm/network.py
catchm/utils.py
CATCHM-0.1.dist-info/METADATA
CATCHM-0.1.dist-info/WHEEL
CATCHM-0.1.dist-info/top_level.txt
CATCHM-0.1.dist-info/RECORD
