Metadata-Version: 2.1
Name: CATCHM
Version: 0.1
Summary: A novel network-based credit card fraud detection approach using noderepresentation learning
Home-page: https://github.com/rafaelvanbelle/CATCHM
Author: Rafael Van Belle
Author-email: rafael@gmail.com
License: UNKNOWN
Platform: UNKNOWN
Classifier: Programming Language :: Python :: 3
Classifier: License :: OSI Approved :: MIT License
Classifier: Operating System :: OS Independent
Requires-Python: >=3.6
Requires-Dist: numpy
Requires-Dist: pandas
Requires-Dist: networkx
Requires-Dist: nodevectors
Requires-Dist: xgboost
Requires-Dist: fucc
Requires-Dist: scikit-learn
